{
  "catalogId": "18e64e3f-3472-499b-9494-e2a983440e58",
  "name": "METHAZOLAMIDE 50MG 100TAB",
  "status": "draft",
  "category": "29C",
  "registrationValidity": "not-registered",
  "registrationNumber": "",
  "treatmentDescriptions": "",
  "termsOfIssue": "Available over-the-counter.",
  "form": "tablet",
  "route": "oral",
  "site": "",
  "method": "",
  "administrationNotes": "",
  "ingredients": "METHAZOLAMIDE 50MG",
  "codes": {},
  "contraindications": "",
  "sideEffect": "",
  "warnings": "",
  "alternativeMedications": [],
  "packaging": [
    {
      "name": "METHAZOLAMIDE 50MG 100TAB",
      "manufacturer": {
        "name": "",
        "countryOfOrigin": "IL"
      },
      "strength": {
        "value": 0,
        "unit": ""
      },
      "quantity": {
        "value": 100.0,
        "unit": "units"
      },
      "packagingDescription": "",
      "shelfLife": "",
      "storageConditions": "",
      "codes": {
        "yarpa": "",
        "pharmasoft": "",
        "moh": "20782"
      },
      "manufacturersAdministrationRecommendation": "",
      "pricing": {}
    }
  ],
  "metadata": {
    "version": "1.4",
    "lastUpdated": "2025-08-01T12:18:43.052533",
    "tags": [
      "failed_il_drug_match"
    ]
  }
}