{
  "catalogId": "212217d7-f936-4e09-8a11-65b09f589835",
  "name": "FERRIPROX TABLETS 1000 MG",
  "status": "draft",
  "category": "prescription",
  "registrationValidity": "valid",
  "registrationNumber": "163 83 35170 00",
  "treatmentDescriptions": "Ferriprox monotherapy is indicated for the treatment of iron overload in patients over 6 years old with thalassaemia major when current chelation therapy is contraindicated or inadequate.Ferriprox in combination with another chelator is indicated in patients with thalassaemia major when monotherapy with any iron chelator is ineffective, or when prevention or treatment of life-threatening consequences of iron overload (mainly cardiac overload) justifies rapid or intensive correction.",
  "termsOfIssue": "Prescription required",
  "form": "film coated tablets",
  "route": "per os",
  "site": "",
  "method": "",
  "administrationNotes": "",
  "ingredients": "DEFERIPRONE",
  "codes": {
    "atc5": {
      "system": "WHO ATC Classification",
      "code": "V03AC02",
      "name": "DEFERIPRONE"
    }
  },
  "contraindications": "",
  "sideEffect": "",
  "warnings": "תרופה מוגבלת לרישום ע'י רופא מומחה או הגבלה אחרת",
  "alternativeMedications": [],
  "packaging": [
    {
      "name": "FERRIPROX 500MG 100TAB",
      "manufacturer": {
        "name": "לפידות",
        "countryOfOrigin": "IL"
      },
      "strength": {
        "value": 0,
        "unit": ""
      },
      "quantity": {
        "value": 100.0,
        "unit": "units"
      },
      "packagingDescription": "BOTTLE HDPE",
      "shelfLife": "48",
      "storageConditions": "",
      "codes": {
        "moh": "6248",
        "yarpa": "70243",
        "pharmasoft": "6421",
        "barcode": "7290018216071"
      },
      "manufacturersAdministrationRecommendation": "",
      "pricing": {
        "currency": "ILS",
        "maxWholesalePrice": 500.5313193,
        "retailMargin": 17.5,
        "maxRetailPrice": 588.1243002,
        "maxPriceWithVAT": 693.9866434
      }
    }
  ],
  "metadata": {
    "version": "1.4",
    "lastUpdated": "2025-07-31T22:09:11.793905"
  }
}