{
  "resourceType": "OpenMedMedication",
  "id": "3006",
  "name": "SANDIMMUN NEO 50MG 50CAPS",
  "meta": {
    "version": "1.3.0",
    "lastUpdated": "2025-07-24T15:35:13.482741",
    "source": "formidable_moh_2025.csv"
  },
  "status": "draft",
  "lifecycleStage": "draft",
  "category": "Prescription Medicine",
  "manufacturer": {
    "name": "נוברטיס פארמה",
    "country": "IL"
  },
  "packaging": [
    {
      "packageSize": 50,
      "unit": "units"
    }
  ],
  "composition": [
    {
      "substance": "SANDIMMUN NEO 50MG 50CAPS"
    }
  ],
  "pricing": {
    "maxWholesalePrice": 222.8635,
    "retailMarginPercent": 17.5,
    "maxRetailPrice": 261.8646125,
    "maxPriceWithVAT": 309.0002428,
    "currency": "ILS"
  },
  "codes": {
    "yarpa": "9079",
    "pharmasoft": "19076",
    "formidable": "FC3006",
    "moh": "3006"
  }
}