{
  "resourceType": "OpenMedMedication",
  "id": "3493",
  "name": "ETOPAN 200MG 20CAPS",
  "meta": {
    "version": "1.3.0",
    "lastUpdated": "2025-07-24T15:34:41.954180",
    "source": "formidable_moh_2025.csv"
  },
  "status": "draft",
  "lifecycleStage": "draft",
  "category": "Prescription Medicine",
  "manufacturer": {
    "name": "תרו",
    "country": "IL"
  },
  "packaging": [
    {
      "packageSize": 20,
      "unit": "units"
    }
  ],
  "composition": [
    {
      "substance": "ETOPAN 200MG 20CAPS"
    }
  ],
  "pricing": {
    "currency": "ILS"
  },
  "codes": {
    "yarpa": "76314",
    "pharmasoft": "5115",
    "formidable": "FC3493",
    "moh": "3493"
  }
}