{
  "catalogId": "44466eeb-f513-4fa7-ac2c-f50102fb56f2",
  "name": "ETOPAN XL 500",
  "status": "draft",
  "category": "prescription",
  "registrationValidity": "valid",
  "registrationNumber": "128 08 30651 00",
  "treatmentDescriptions": "For the management of signs and symptoms of osteoarthrities and rheumatoid arthritis.",
  "termsOfIssue": "Prescription required",
  "form": "tablets extended release",
  "route": "per os",
  "site": "",
  "method": "",
  "administrationNotes": "",
  "ingredients": "ETODOLAC",
  "codes": {
    "atc5": {
      "system": "WHO ATC Classification",
      "code": "M01AB08",
      "name": "ETODOLAC"
    }
  },
  "contraindications": "",
  "sideEffect": "",
  "warnings": "",
  "alternativeMedications": [],
  "packaging": [
    {
      "name": "ETOPAN 500MG 20TAB",
      "manufacturer": {
        "name": "תרו",
        "countryOfOrigin": "IL"
      },
      "strength": {
        "value": 0,
        "unit": ""
      },
      "quantity": {
        "value": 20.0,
        "unit": "units"
      },
      "packagingDescription": "BOTTLE HDPE",
      "shelfLife": "36",
      "storageConditions": "",
      "codes": {
        "moh": "6858",
        "yarpa": "16271",
        "pharmasoft": "5522"
      },
      "manufacturersAdministrationRecommendation": "",
      "pricing": {
        "currency": "ILS",
        "maxWholesalePrice": "",
        "retailMargin": "",
        "maxRetailPrice": "",
        "maxPriceWithVAT": ""
      }
    }
  ],
  "metadata": {
    "version": "1.4",
    "lastUpdated": "2025-07-31T22:09:12.142720"
  }
}