{
  "catalogId": "510718ad-8bca-4ca0-8dfe-5efa072bc89c",
  "name": "SITAGLIPTIN S.K. 100 MG",
  "status": "draft",
  "category": "prescription",
  "registrationValidity": "valid",
  "registrationNumber": "171 99 36508 99",
  "treatmentDescriptions": "Sitagliptin S.K. is indicated as an adjunct to diet and exercise to improve glycemic control in adults with type 2 diabetes melitus. Important limitations of use: Sitagliptin S.K. should not be used in patients with type 1 diabetes or for the treatment of diabetic ketoacidosis as it would not be effective in these settings. Sitagliptin S.K. has not been studied in patients with a history of pancreatitis. It is unknown whether patients with a history of pancreatitis are at increased risk for the development of pancreatitis while using Sitagliptin S.K..",
  "termsOfIssue": "Prescription required",
  "form": "film coated tablets",
  "route": "per os",
  "site": "",
  "method": "",
  "administrationNotes": "",
  "ingredients": "SITAGLIPTIN AS HYDROCHLORIDE MONOHYDRATE",
  "codes": {
    "atc5": {
      "system": "WHO ATC Classification",
      "code": "A10BH01",
      "name": "SITAGLIPTIN"
    }
  },
  "contraindications": "",
  "sideEffect": "",
  "warnings": "",
  "alternativeMedications": [],
  "packaging": [
    {
      "name": "SITAGLIPTIN S.K. 50 MG 30 TAB",
      "manufacturer": {
        "name": "SK PHARM(KS KIM)",
        "countryOfOrigin": "IL"
      },
      "strength": [
        {
          "value": 50.0,
          "unit": "mg"
        }
      ],
      "quantity": {
        "value": 30.0,
        "unit": "units"
      },
      "packagingDescription": "BLISTER PVC/PE/PVDC/AL",
      "shelfLife": "24",
      "storageConditions": "",
      "codes": {
        "moh": "9445",
        "yarpa": "22233"
      },
      "manufacturersAdministrationRecommendation": "",
      "pricing": {
        "currency": "ILS",
        "maxWholesalePrice": 80.16,
        "retailMargin": 34.5,
        "maxRetailPrice": 107.8152,
        "maxPriceWithVAT": 127.221936
      }
    }
  ],
  "metadata": {
    "version": "1.4",
    "lastUpdated": "2025-08-01T17:44:01.800448",
    "tags": [
      "needs_manual_review"
    ],
    "availableApiOptions": [
      {
        "name": "JANUET XR 100/1000 MG TABLETS",
        "registration": "151 33 33934 00",
        "form": ""
      },
      {
        "name": "JANUET XR 100/1000 MG TABLETS",
        "registration": "151 33 33934 02",
        "form": ""
      },
      {
        "name": "JANUET 50 MG/1000 MG",
        "registration": "139 88 31705 14",
        "form": ""
      }
    ],
    "smartValidation": {
      "extractedFrom": "SITAGLIPTIN S.K. 50 MG 30 TAB",
      "processedBy": "smart_validation",
      "bestMatchScore": 0.2111111111111111,
      "status": "failed_match"
    }
  }
}