{
  "resourceType": "OpenMedMedication",
  "id": "5458",
  "name": "BITNI X SUSPENSION 100 ML",
  "meta": {
    "version": "1.3.0",
    "lastUpdated": "2025-07-24T15:35:23.471740",
    "source": "formidable_moh_2025.csv"
  },
  "status": "draft",
  "lifecycleStage": "draft",
  "category": "Off the Counter",
  "manufacturer": {
    "name": "כ.צ.ט",
    "country": "IL"
  },
  "packaging": [
    {
      "packageSize": 100,
      "unit": "units"
    }
  ],
  "composition": [
    {
      "substance": "BITNI X SUSPENSION 100 ML"
    }
  ],
  "pricing": {
    "maxRetailPrice": 20.93,
    "maxPriceWithVAT": 24.6974,
    "currency": "ILS"
  },
  "codes": {
    "formidable": "FC5458",
    "moh": "5458"
  }
}