{
  "catalogId": "577bd452-e7d6-493c-ad96-7b2ad5cff43e",
  "name": "CAPECITABINE TEVA ® 150 MG",
  "status": "draft",
  "category": "prescription",
  "registrationValidity": "valid",
  "registrationNumber": "152 61 34182 00",
  "treatmentDescriptions": "Adjuvant Colon Cancer: Capecitabine Teva® is indicated for the adjuvant treatment of patients following surgery of stage III (Dukesע stage C) colon cancer. Colorectal Cancer: Capecitabine Teva® is indicated for the treatment of patients with advanced or metastatic colorectal cancer. Advanced gastric cancer: Capecitabine Teva® is indicated for first line treatment of advanced gastric cancer in combination with chemotherapy. Breast Cancer Combination Therapy: Capecitabine Teva® in combination with docetaxel is indicated for the treatment of patients with metastatic breast cancer after failure of prior anthracycline-containing chemotherapy. Breast Cancer Monotherapy: Capecitabine Teva® is also indicated for the treatment of advanced or metastatic breast cancer after failure of standard therapy including a taxane unless therapy with a taxane is clinically contraindicated.",
  "termsOfIssue": "Prescription required",
  "form": "film coated tablets",
  "route": "per os",
  "site": "",
  "method": "",
  "administrationNotes": "",
  "ingredients": "CAPECITABINE",
  "codes": {
    "atc5": {
      "system": "WHO ATC Classification",
      "code": "L01BC06",
      "name": "CAPECITABINE"
    }
  },
  "contraindications": "",
  "sideEffect": "",
  "warnings": "תרופה מוגבלת לרישום ע'י רופא מומחה או הגבלה אחרת",
  "alternativeMedications": [],
  "packaging": [
    {
      "name": "CAPECITABINE TEVA 150MG 60TAB",
      "manufacturer": {
        "name": "טבע",
        "countryOfOrigin": "IL"
      },
      "strength": {
        "value": 0,
        "unit": ""
      },
      "quantity": {
        "value": 60.0,
        "unit": "units"
      },
      "packagingDescription": "BLISTER PVC/PE/PVDC/AL",
      "shelfLife": "24",
      "storageConditions": "",
      "codes": {
        "moh": "7546",
        "yarpa": "57488",
        "pharmasoft": "9774",
        "barcode": "7290106061460"
      },
      "manufacturersAdministrationRecommendation": "",
      "pricing": {
        "currency": "ILS",
        "maxWholesalePrice": 95.5833,
        "retailMargin": 25.0,
        "maxRetailPrice": 119.479125,
        "maxPriceWithVAT": 140.9853675
      }
    }
  ],
  "metadata": {
    "version": "1.4",
    "lastUpdated": "2025-07-31T22:09:12.314602"
  }
}