{
  "resourceType": "OpenMedMedication",
  "id": "6143",
  "name": "SIFROL 1.0 MG 100 TAB",
  "meta": {
    "version": "1.3.0",
    "lastUpdated": "2025-07-24T15:35:14.164746",
    "source": "formidable_moh_2025.csv"
  },
  "status": "draft",
  "lifecycleStage": "draft",
  "category": "Prescription Medicine",
  "manufacturer": {
    "name": "בורינגר אינגלהיים",
    "country": "IL"
  },
  "packaging": [
    {
      "packageSize": 100,
      "unit": "units"
    }
  ],
  "composition": [
    {
      "substance": "SIFROL 1.0 MG 100 TAB"
    }
  ],
  "pricing": {
    "maxWholesalePrice": 223.17869,
    "retailMarginPercent": 17.5,
    "maxRetailPrice": 262.2349608,
    "maxPriceWithVAT": 309.4372399,
    "currency": "ILS"
  },
  "codes": {
    "yarpa": "17218",
    "pharmasoft": "9791",
    "formidable": "FC6143",
    "moh": "6143"
  }
}