{
  "resourceType": "OpenMedMedication",
  "id": "6611",
  "name": "METHADONE 5% 50MG/ML 25 BOTTLE/ 200ML",
  "meta": {
    "version": "1.3.0",
    "lastUpdated": "2025-07-24T15:34:59.870654",
    "source": "formidable_moh_2025.csv"
  },
  "status": "draft",
  "lifecycleStage": "draft",
  "category": "Prescription Medicine",
  "manufacturer": {
    "name": "רפא",
    "country": "IL"
  },
  "packaging": [
    {
      "packageSize": 25,
      "unit": "units"
    }
  ],
  "composition": [
    {
      "substance": "METHADONE 5% 50MG/ML 25 BOTTLE/ 200ML"
    }
  ],
  "pricing": {
    "currency": "ILS"
  },
  "codes": {
    "yarpa": "35291",
    "pharmasoft": "13138",
    "formidable": "FC6611",
    "moh": "6611"
  }
}