{
  "catalogId": "7805b16b-81a4-4c8e-a548-3296d67a208c",
  "name": "IODIFLOR OINTMENT",
  "status": "draft",
  "category": "off-the-counter",
  "registrationValidity": "valid",
  "registrationNumber": "141 02 31802 00",
  "treatmentDescriptions": "For the disinfection of skin infections and inflammations, wounds and superficial burns.",
  "termsOfIssue": "",
  "form": "ointment",
  "route": "dermal",
  "site": "",
  "method": "",
  "administrationNotes": "",
  "ingredients": "POVIDONE-IODINE",
  "codes": {
    "atc5": {
      "system": "WHO ATC Classification",
      "code": "D08AG03",
      "name": "IODINE"
    }
  },
  "contraindications": "",
  "sideEffect": "",
  "warnings": "",
  "alternativeMedications": [],
  "packaging": [
    {
      "name": "IODIFLOR OINTMENT 50 GR",
      "manufacturer": {
        "name": "פלוריש",
        "countryOfOrigin": "IL"
      },
      "strength": {
        "value": 0,
        "unit": ""
      },
      "quantity": {
        "value": 50.0,
        "unit": "units"
      },
      "packagingDescription": "BOTTLE HDPE",
      "shelfLife": "36",
      "storageConditions": "",
      "codes": {
        "moh": "5533",
        "barcode": "7290006411907"
      },
      "manufacturersAdministrationRecommendation": "",
      "pricing": {
        "currency": "ILS",
        "maxWholesalePrice": "",
        "retailMargin": "",
        "maxRetailPrice": 17.13,
        "maxPriceWithVAT": 20.2134
      }
    }
  ],
  "metadata": {
    "version": "1.4",
    "lastUpdated": "2025-08-01T12:18:43.613724"
  }
}