{
  "catalogId": "81a1a19b-212f-4fe9-af45-989ba062f0fb",
  "name": "OXACATIN",
  "status": "",
  "category": "prescription",
  "registrationValidity": "valid",
  "registrationNumber": "030 54 21959 00",
  "treatmentDescriptions": "Antitussive expectorant.",
  "termsOfIssue": "Prescription required",
  "form": "syrup",
  "route": "per os",
  "site": "",
  "method": "",
  "administrationNotes": "",
  "ingredients": "OXOMEMAZINE 1.65  MG /, BENZOIC ACID AS SODIUM 33.3  MG /, GUAIACOLSULFONATE AS POTASSIUM 33.3  MG /",
  "codes": {
    "atc5": {
      "system": "WHO ATC Classification",
      "code": "R06AD08",
      "name": "OXOMEMAZINE"
    }
  },
  "contraindications": "",
  "sideEffect": "",
  "warnings": "",
  "alternativeMedications": [],
  "packaging": [
    {
      "name": "OXACATIN SYR 120ML",
      "manufacturer": {
        "name": "תרו",
        "countryOfOrigin": "IL"
      },
      "strength": {
        "value": 0,
        "unit": ""
      },
      "quantity": {
        "value": 120.0,
        "unit": "units"
      },
      "packagingDescription": "BOTTLE POLYETHYLENE",
      "shelfLife": "24",
      "storageConditions": "",
      "codes": {
        "moh": "3351",
        "yarpa": "9649",
        "pharmasoft": "15017"
      },
      "manufacturersAdministrationRecommendation": "",
      "pricing": {
        "currency": "ILS",
        "maxWholesalePrice": NaN,
        "retailMargin": NaN,
        "maxRetailPrice": NaN,
        "maxPriceWithVAT": NaN
      }
    }
  ],
  "metadata": {
    "version": "1.4",
    "lastUpdated": "2025-07-31T06:20:05.311852"
  }
}