{
  "catalogId": "c1fda98c-58a9-44aa-bd12-1cd6d0aba825",
  "name": "XENPOZYME",
  "status": "draft",
  "category": "prescription",
  "registrationValidity": "valid",
  "registrationNumber": "173 41 37455 00",
  "treatmentDescriptions": "Xenpozyme is indicated as an enzyme replacement therapy for the treatment of non-Central Nervous System (CNS) manifestations of Acid Sphingomyelinase Deficiency (ASMD) in paediatric and adult patients with type A/B or type B",
  "termsOfIssue": "Prescription required",
  "form": "powder for concentrate for solution for infusion",
  "route": "i.v",
  "site": "",
  "method": "",
  "administrationNotes": "",
  "ingredients": "OLIPUDASE ALFA/VIAL",
  "codes": {
    "atc5": {
      "system": "WHO ATC Classification",
      "code": "A16AB25",
      "name": "OLIPUDASE ALFA"
    }
  },
  "contraindications": "",
  "sideEffect": "",
  "warnings": "",
  "alternativeMedications": [],
  "packaging": [
    {
      "name": "XENPOZYME 1 VIAL",
      "manufacturer": {
        "name": "סאנופי אוונטיס",
        "countryOfOrigin": "IL"
      },
      "strength": [],
      "quantity": {
        "value": 1.0,
        "unit": "units"
      },
      "packagingDescription": "VIAL GLASS TYPE I",
      "shelfLife": "48",
      "storageConditions": "",
      "codes": {
        "moh": "9277",
        "yarpa": "30222"
      },
      "manufacturersAdministrationRecommendation": "",
      "pricing": {
        "currency": "ILS",
        "maxWholesalePrice": 12825.06711,
        "retailMargin": 10.0,
        "maxRetailPrice": 14107.57382,
        "maxPriceWithVAT": 16646.93637
      },
      "formulation": ""
    }
  ],
  "metadata": {
    "version": "1.5",
    "lastUpdated": "2025-08-01T18:03:53.256397"
  }
}