{
  "catalogId": "e1fcb75a-852e-47e1-bf8c-82d92569dcac",
  "name": "FOROL TABLETS",
  "status": "",
  "category": "off-the-counter",
  "registrationValidity": "valid",
  "registrationNumber": "154 68 34101 00",
  "treatmentDescriptions": "For the prevention and treatment of iron deficiency anemia and for maintaining the level of folic acid particular in pregnancy.",
  "termsOfIssue": "",
  "form": "tablets",
  "route": "per os",
  "site": "",
  "method": "",
  "administrationNotes": "",
  "ingredients": "FOLIC ACID, FERROUS FUMARATE",
  "codes": {},
  "contraindications": "",
  "sideEffect": "",
  "warnings": " ",
  "alternativeMedications": [],
  "packaging": [
    {
      "name": "FOROL 30 TABLETS",
      "manufacturer": {
        "name": "סם און",
        "countryOfOrigin": "IL"
      },
      "strength": {
        "value": 0,
        "unit": ""
      },
      "quantity": {
        "value": 30.0,
        "unit": "units"
      },
      "packagingDescription": "BLISTER PVC/ALUMINIUM",
      "shelfLife": "36",
      "storageConditions": "",
      "codes": {
        "moh": "5503"
      },
      "manufacturersAdministrationRecommendation": "",
      "pricing": {
        "currency": "ILS",
        "maxWholesalePrice": NaN,
        "retailMargin": NaN,
        "maxRetailPrice": 35.07,
        "maxPriceWithVAT": 41.3826
      }
    }
  ],
  "metadata": {
    "version": "1.4",
    "lastUpdated": "2025-07-31T11:57:43.506707"
  }
}