{
  "catalogId": "ee0ee889-3a57-45f0-852b-3b7faf8ad66a",
  "name": "TRITTICO 100 MG",
  "status": "draft",
  "category": "prescription",
  "registrationValidity": "valid",
  "registrationNumber": "173 31 36296 00",
  "treatmentDescriptions": "For the treatment of depression with or without anxiety.",
  "termsOfIssue": "Prescription required",
  "form": "tablets",
  "route": "per os",
  "site": "",
  "method": "",
  "administrationNotes": "",
  "ingredients": "TRAZODONE HYDROCHLORIDE",
  "codes": {
    "atc5": {
      "system": "WHO ATC Classification",
      "code": "N06AX05",
      "name": "TRAZODONE"
    }
  },
  "contraindications": "",
  "sideEffect": "",
  "warnings": "",
  "alternativeMedications": [],
  "packaging": [
    {
      "name": "TRITTICO 100 MG 30 tabs",
      "manufacturer": {
        "name": "רז פרמהצפטי",
        "countryOfOrigin": "IL"
      },
      "strength": {
        "value": 0,
        "unit": ""
      },
      "quantity": {
        "value": 30.0,
        "unit": "units"
      },
      "packagingDescription": "BLISTER PVC/ALUMINIUM",
      "shelfLife": "48",
      "storageConditions": "",
      "codes": {
        "moh": "9316",
        "yarpa": "77179",
        "barcode": "7290015863629"
      },
      "manufacturersAdministrationRecommendation": "",
      "pricing": {
        "currency": "ILS",
        "maxWholesalePrice": 29.893554,
        "retailMargin": 37.0,
        "maxRetailPrice": 40.95416898,
        "maxPriceWithVAT": 48.32591725
      }
    }
  ],
  "metadata": {
    "version": "1.4",
    "lastUpdated": "2025-07-31T22:09:13.777299"
  }
}